{"PresentParticiple":"hablando&translation=speaking","PastParticiple":"hablado&translation=spoken","Indicative":{"PresentTense":{"Yo":"hablo","Tu":"hablas","ElEllaUsted":"habla","Nosotros":"hablamos","Vosotros":"habláis","EllosEllasUstedes":"hablan"},"Pretérito":{"Yo":"hablé","Tu":"hablaste","ElEllaUsted":"habló","Nosotros":"hablamos","Vosotros":"hablasteis","EllosEllasUstedes":"hablaron"},"Imperfect":{"Yo":"hablaba","Tu":"hablabas","ElEllaUsted":"hablaba","Nosotros":"hablábamos","Vosotros":"hablabais","EllosEllasUstedes":"hablaban"},"Conditional":{"Yo":"hablaría","Tu":"hablarías","ElEllaUsted":"hablaría","Nosotros":"hablaríamos","Vosotros":"hablaríais","EllosEllasUstedes":"hablarían"},"Future":{"Yo":"hablaré","Tu":"hablarás","ElEllaUsted":"hablará","Nosotros":"hablaremos","Vosotros":"hablaréis","EllosEllasUstedes":"hablarán"}},"Subjunctive":null,"Name":"hablar","EnglishMeaning":"to speak"}